SQRT/control_SQRT.v
module control_SQRT(
                   input clk,
                   input rst,
                   input init,
                   input S,
                   input [3:0]j,

                   output reg rs,
                   output reg cct,
                   output reg dc,
                   output reg s,
                   output reg sh,
                   output reg done
                   );
  parameter START  = 3'b000;
  parameter CONCAT = 3'b001;
  parameter DEC    = 3'b010;
  parameter CHECK1 = 3'b011;
  parameter ASIG   = 3'b100;
  parameter SHIFT  = 3'b101;
  parameter CHECK2 = 3'b110;
  parameter DONE   = 3'b111;

reg [3:0] state;

initial begin
    rs = 0;
    dc = 0;

  end

reg [3:0]count;

  always @(posedge clk) begin
    if (rst)
      state = START;
    else begin
      case(state)

      START:begin
        count=0;
        if (init)
          state = CONCAT;
        else
          state = START;
      end

      CONCAT:
        state = DEC;

      DEC:
        state = CHECK1;

      CHECK1:begin
        if (S)
          state = SHIFT;
        else
          state = ASIG;
      end

      ASIG:
        state = SHIFT;

      SHIFT:
        state = CHECK2;

      CHECK2:
        if (j)
          state = DONE;
        else
          state = CONCAT;

      DONE:begin
        count = count + 1;
        if (count>9)
          state = START;
        else
          state = DONE;
      end

      default:
        state = START;

      endcase
    end
  end

  always @ (state) begin
    case (state)

      START:begin
        rs   = 1;
        cct  = 0;
        dc   = 0;
        s    = 0;
        sh   = 0;
        done = 0;
      end

      CONCAT:begin
        rs   = 0;
        cct  = 1;
        dc   = 0;
        s    = 0;
        sh   = 0;
        done = 0;
      end

      DEC:begin
        rs   = 0;
        cct  = 0;
        dc   = 1;
        s    = 0;
        sh   = 0;
        done = 0;
      end

      CHECK1:begin
        rs   = 0;
        cct  = 0;
        dc   = 0;
        s    = 0;
        sh   = 0;
        done = 0;
      end

      ASIG:begin
        rs   = 0;
        cct  = 0;
        dc   = 0;
        s    = 1;
        sh   = 0;
        done = 0;
      end

      SHIFT:begin
        rs   = 0;
        cct  = 0;
        dc   = 0;
        s    = 0;
        sh   = 1;
        done = 0;
      end

      CHECK2:begin
        rs   = 0;
        cct  = 0;
        dc   = 0;
        s    = 0;
        sh   = 0;
        done = 0;
      end

      DONE:begin
        rs   = 0;
        cct  = 0;
        dc   = 0;
        s    = 0;
        sh   = 0;
        done = 1;
      end

      default:begin
        rs   = 0;
        cct  = 0;
        dc   = 0;
        s    = 0;
        sh   = 0;
        done = 0;
      end
    endcase
  end
endmodule

SQRT/cont.v
module cont(
            input clk,
            input rs,
            input sh,
            output reg [3:0]j
            );

initial j = 0;

 always @ ( posedge clk) begin
   if (rs) begin
    j = 4'b0100;
    if (sh)
      j = j - 4'b0001;
    else
      j = j;
    end
  end
endmodule

SQRT/comp2.v
module comp2(
             input [5:0]T,
             output reg [6:0]c2
             );

  always @ (*) begin
    c2 = ~T;
    c2 = c2 + 01;
  end
endmodule

SQRT/dec.v
module dec(
           input clk,
           input rs,
           input dc,
           input [6:0]c2,
           input [8:0]R,
           output reg [8:0]S
           );
  initial S = 0;

  always @ (negedge clk)
    if (rs)
      S = R;
    else begin
      if (dc)
        S = S + c2;
      else
        S = S;
    end
endmodule

SQRT/tcct.v
module tcct(
            input clk,
            input rs,
            input cct,
            input [4:0] Q,
            output reg [5:0] T
            );

  always @(negedge clk) begin
    if (rs)
      T = 0;
    if (cct) begin
      T = Q << 2;
      T = T + 01;
    end
    else
      T = T;
  end
endmodule

SQRT/rcct.v
module rcct(
            input clk,
            input rs,
            input cct,
            input s,
            input [1:0]A,
            input [8:0]S,
            output reg [8:0]R
            );

  always @(negedge clk) begin
    if (rs)
      R = 0;
    if (cct)
      R = {R, A};
    if (s)
      R = S;
    else
      R = R;
  end
endmodule

SQRT/qcct.v
module qcct(
            input clk,
            input rs,
            input cct,
            input sh,
            input S,
            output reg [4:0]Q
            );

  always @(negedge clk) begin
    if (rs)
      Q = 0;
    if (sh) begin
      //esto es concatenación de forma burda pero creo que sí serviría en caso dado, (corrimiento izquierda) + S
      //Q = Q << 1;
      //Q = Q + S;
      Q = {Q, S};
    end
    else
      Q = Q;
  end
endmodule

SQRT/lsr.v
module lsr(
           input clk,
           input rs,
           input sh,
           input [7:0]i,
           output reg [7:0]o
           );

  always @(negedge clk)
    if (rs)
      o = i;
    else begin
      if (sh)
        o = o << 2;
      else
        o = o;
    end
endmodule

SQRT/SQRT.v
module SQRT(
            input clk,
            input init,
            input rst,
            input [7:0] A,
            output [4:0] Q,
            output [8:0] R,
            output done);

            wire w_rs;
            wire w_cct;
            wire w_dc;
            wire w_s;
            wire w_sh;

            wire [7:0] w_A;
            wire [5:0] T;
            wire [6:0] w_T;
            wire [8:0] w_S;
            wire [3:0] w_j;

            lsr lsr0 (.clk(clk), .rs(w_rs), .sh(w_sh),
                      .i(A),
                      .o(w_A));

            qcct qcct0 (.clk(clk), .rs(w_rs), .sh(w_sh),
                        .S(w_S[8]),
                        .Q(Q));

            rcct rcct0 (.clk(clk), .rs(w_rs), .cct(w_cct), .s(w_s),
                        .A(w_A[7:6]), .S(w_S),
                        .R(R));

            tcct tcct0 (.clk(clk), .rs(w_rs), .cct(w_cct),
                          .Q(Q),
                          .T(T));

            dec dec0 (.clk(clk), .rs(w_rs), .dc(w_dc),
                      .R(R), .c2(w_T),
                      .S(w_S));

            comp2 comp20 (.T(T),
                          .c2(w_T));

            cont cont0 (.clk(clk), .rs(w_rs), .sh(w_sh),
                        .j(w_j));

            control_SQRT control_SQRT0 (.clk(clk), .rst(rst), .init(init), .S(w_S[8]), .j(w_j),
                                        .rs(w_rs), .cct(w_cct), .dc(w_dc), .s(w_s), .sh(w_sh), .done(done));
endmodule

SQRT/SQRT_TB.v
`timescale 1ns / 1ps
`define SIMULATION

module SQRT_TB;
  reg clk;
  reg init;
  reg rst;
  reg [7:0] A;

  wire [4:0] Q;
  wire [8:0] R;
  wire done;

  SQRT uut (.clk(clk), .init(init), .rst(rst), .A(A),
            .Q(Q), .R(R), .done(done));
  parameter          PERIOD = 20;
  parameter real DUTY_CYCLE = 0.5;
  parameter          OFFSET = 0;

    event reset_trigger;
    event reset_done_trigger;
    initial begin
      forever begin
        @(reset_trigger);
        @(negedge clk); rst = 1;
        @(negedge clk); rst = 0;
        -> reset_done_trigger;
      end
    end

  initial begin
    clk  = 0;
    init = 0;
    rst  = 0;
    A    = 8'b00110010;
  end

  initial begin
    #OFFSET;
    forever begin
      clk = 1'b0;
      #(PERIOD-(PERIOD*DUTY_CYCLE)) clk = 1'b1;
      #(PERIOD*DUTY_CYCLE);
    end
  end

  reg [20:0] i;
  initial begin
    #10 -> reset_trigger;
    @ (reset_done_trigger);
    @ (posedge clk); init = 0;
    @ (posedge clk); init = 1;
    for (i = 0; i < 2; i = i + 1) begin
      @ (posedge clk);
    end
    init = 0;
    for (i = 0; i < 25; i = i + 1) begin
      @ (posedge clk);
    end
  end


  initial begin: TEST_CASE
    $dumpfile("SQRT_TB.vcd");
    $dumpvars(-1, uut);
    #((PERIOD*DUTY_CYCLE)*200)$finish;
  end
endmodule

SQRT/SQRT_TB.vcd
$date
	Wed Jul 15 12:20:28 2026
$end
$version
	Icarus Verilog
$end
$timescale
	1ps
$end
$scope module SQRT_TB $end
$scope module uut $end
$var wire 8 ! A [7:0] $end
$var wire 1 " clk $end
$var wire 1 # init $end
$var wire 1 $ rst $end
$var wire 1 % w_sh $end
$var wire 1 & w_s $end
$var wire 1 ' w_rs $end
$var wire 4 ( w_j [3:0] $end
$var wire 1 ) w_dc $end
$var wire 1 * w_cct $end
$var wire 7 + w_T [6:0] $end
$var wire 9 , w_S [8:0] $end
$var wire 8 - w_A [7:0] $end
$var wire 1 . done $end
$var wire 6 / T [5:0] $end
$var wire 9 0 R [8:0] $end
$var wire 5 1 Q [4:0] $end
$scope module comp20 $end
$var wire 6 2 T [5:0] $end
$var reg 7 3 c2 [6:0] $end
$upscope $end
$scope module cont0 $end
$var wire 1 " clk $end
$var wire 1 % sh $end
$var wire 1 ' rs $end
$var reg 4 4 j [3:0] $end
$upscope $end
$scope module control_SQRT0 $end
$var wire 1 5 S $end
$var wire 1 " clk $end
$var wire 1 # init $end
$var wire 4 6 j [3:0] $end
$var wire 1 $ rst $end
$var parameter 3 7 ASIG $end
$var parameter 3 8 CHECK1 $end
$var parameter 3 9 CHECK2 $end
$var parameter 3 : CONCAT $end
$var parameter 3 ; DEC $end
$var parameter 3 < DONE $end
$var parameter 3 = SHIFT $end
$var parameter 3 > START $end
$var reg 1 * cct $end
$var reg 4 ? count [3:0] $end
$var reg 1 ) dc $end
$var reg 1 . done $end
$var reg 1 ' rs $end
$var reg 1 & s $end
$var reg 1 % sh $end
$var reg 4 @ state [3:0] $end
$upscope $end
$scope module dec0 $end
$var wire 7 A c2 [6:0] $end
$var wire 1 " clk $end
$var wire 1 ) dc $end
$var wire 1 ' rs $end
$var wire 9 B R [8:0] $end
$var reg 9 C S [8:0] $end
$upscope $end
$scope module lsr0 $end
$var wire 1 " clk $end
$var wire 8 D i [7:0] $end
$var wire 1 ' rs $end
$var wire 1 % sh $end
$var reg 8 E o [7:0] $end
$upscope $end
$scope module qcct0 $end
$var wire 1 F S $end
$var wire 1 G cct $end
$var wire 1 " clk $end
$var wire 1 ' rs $end
$var wire 1 % sh $end
$var reg 5 H Q [4:0] $end
$upscope $end
$scope module rcct0 $end
$var wire 2 I A [1:0] $end
$var wire 9 J S [8:0] $end
$var wire 1 * cct $end
$var wire 1 " clk $end
$var wire 1 ' rs $end
$var wire 1 & s $end
$var reg 9 K R [8:0] $end
$upscope $end
$scope module tcct0 $end
$var wire 5 L Q [4:0] $end
$var wire 1 * cct $end
$var wire 1 " clk $end
$var wire 1 ' rs $end
$var reg 6 M T [5:0] $end
$upscope $end
$upscope $end
$upscope $end
$enddefinitions $end
$comment Show the parameter values. $end
$dumpall
b0 >
b101 =
b111 <
b10 ;
b1 :
b110 9
b11 8
b100 7
$end
#0
$dumpvars
bx M
bx L
bx K
b0 J
bx I
bx H
zG
0F
bx E
b110010 D
b0 C
bx B
bx A
bx @
bx ?
b0 6
05
b0 4
bx 3
bx 2
bx 1
bx 0
bx /
x.
bx -
b0 ,
bx +
x*
0)
b0 (
0'
x&
x%
0$
0#
0"
b110010 !
$end
#10000
0.
0%
0&
0*
1'
b0 @
1"
#20000
b0 +
b0 3
b0 A
b0 I
b0 /
b0 2
b0 M
b0 0
b0 B
b0 K
b0 1
b0 H
b0 L
b110010 -
b110010 E
1$
0"
#30000
b100 (
b100 4
b100 6
1"
#40000
0$
0"
#50000
b0 ?
1"
#60000
0"
#70000
1#
1"
#80000
0"
#90000
1*
0'
b1 @
1"
#100000
b1111111 +
b1111111 3
b1111111 A
b1 /
b1 2
b1 M
0"
#110000
1)
0*
0#
b10 @
1"
#120000
b1111111 ,
b1111111 C
b1111111 J
0"
#130000
0)
b11 @
1"
#140000
0"
#150000
1&
b100 @
1"
#160000
b1111111 0
b1111111 B
b1111111 K
0"
#170000
1%
0&
b101 @
1"
#180000
b11 I
b11001000 -
b11001000 E
0"
#190000
0%
b110 @
1"
#200000
0"
#210000
1.
b111 @
1"
#220000
0"
#230000
b1 ?
1"
#240000
0"
#250000
b10 ?
1"
#260000
0"
#270000
b11 ?
1"
#280000
0"
#290000
b100 ?
1"
#300000
0"
#310000
b101 ?
1"
#320000
0"
#330000
b110 ?
1"
#340000
0"
#350000
b111 ?
1"
#360000
0"
#370000
b1000 ?
1"
#380000
0"
#390000
b1001 ?
1"
#400000
0"
#410000
0.
1'
b0 @
b1010 ?
1"
#420000
b0 +
b0 3
b0 A
b0 I
b0 ,
b0 C
b0 J
b0 /
b0 2
b0 M
b0 0
b0 B
b0 K
b110010 -
b110010 E
0"
#430000
b0 ?
1"
