SQRT/control_SQRT.v
module control_SQRT(
                   input clk,
                   input rst,
                   input init,
                   input S,
                   input j,

                   output reg rs,
                   output reg cct,
                   output reg dc,
                   output reg s,
                   output reg sh,
                   output reg done
                   );
  parameter START  = 3'b000;
  parameter CONCAT = 3'b001;
  parameter DEC    = 3'b010;
  parameter CHECK1 = 3'b011;
  parameter ASIG   = 3'b100;
  parameter SHIFT  = 3'b101;
  parameter CHECK2 = 3'b110;
  parameter DONE   = 3'b111;

reg [3:0] state;

initial begin
    rs = 0;
    dc = 0;

  end

reg [3:0]count;

  always @(posedge clk) begin
    if (rst)
      state = START;
    else begin
      case(state)

      START:begin
        count=0;
        if (init)
          state = CONCAT;
        else
          state = START;
      end

      CONCAT:
        state = DEC;

      DEC:
        state = CHECK1;

      CHECK1:begin
        if (S)
          state = SHIFT;
        else
          state = ASIG;
      end

      ASIG:
        state = SHIFT;

      SHIFT:
        state = CHECK2;

      CHECK2:
        if (j)
          state = DONE;
        else
          state = CONCAT;

      DONE:begin
        count = count + 1;
        if (count>9)
          state = START;
        else
          state = DONE;
      end

      default:
        state = START;

      endcase
    end
  end

  always @ (state) begin
    case (state)

      START:begin
        rs   = 1;
        cct  = 0;
        dc   = 0;
        s    = 0;
        sh   = 0;
        done = 0;
      end

      CONCAT:begin
        rs   = 0;
        cct  = 1;
        dc   = 0;
        s    = 0;
        sh   = 0;
        done = 0;
      end

      DEC:begin
        rs   = 0;
        cct  = 0;
        dc   = 1;
        s    = 0;
        sh   = 0;
        done = 0;
      end

      CHECK1:begin
        rs   = 0;
        cct  = 0;
        dc   = 0;
        s    = 0;
        sh   = 0;
        done = 0;
      end

      ASIG:begin
        rs   = 0;
        cct  = 0;
        dc   = 0;
        s    = 1;
        sh   = 0;
        done = 0;
      end

      SHIFT:begin
        rs   = 0;
        cct  = 0;
        dc   = 0;
        s    = 0;
        sh   = 1;
        done = 0;
      end

      CHECK2:begin
        rs   = 0;
        cct  = 0;
        dc   = 0;
        s    = 0;
        sh   = 0;
        done = 0;
      end

      DONE:begin
        rs   = 0;
        cct  = 0;
        dc   = 0;
        s    = 0;
        sh   = 0;
        done = 1;
      end

      default:begin
        rs   = 0;
        cct  = 0;
        dc   = 0;
        s    = 0;
        sh   = 0;
        done = 0;
      end
    endcase
  end
endmodule

SQRT/cont.v
module cont(
            input clk,
            input rs,
            input sh,
            output wire j
            );

reg [2:0] h;

 always @ ( posedge clk) begin
   if (rs)
     h = 3'd4;
   if (sh) begin
     if (h > 0)
       h = h - 3'd1;
    end
  end
    assign j = (h == 3'd0);
endmodule

SQRT/comp2.v
module comp2(
             input clk,
             input cct,
             input [7:0]T,
             output reg [7:0]c2
             );

  always @(negedge clk)
    if (cct) begin
      c2 = ~T + 8'b00000001;
    end
endmodule

SQRT/dec.v
module dec(
           input clk,
           input rs,
           input dc,
           input [7:0]c2,
           input [7:0]R,
           output reg [7:0]S
           );
  initial S = 0;

  always @ (negedge clk)
    if (rs)
      S = 8'b0;
    else begin
      if (dc) begin
        S = R + c2;
        //S = S + c2;
        //if (S[7])
          //S = R;
        //else
          //S = S + c2;
      end
    end
endmodule

SQRT/tcct.v
module tcct(
            input clk,
            input rs,
            input cct,
            input [7:0] Q,
            output reg [7:0] T
            );

  always @(negedge clk) begin
    if (rs)
      T = 8'b0;
    if (cct) begin
      T = (Q << 2) + 8'b00000001;
    end
    else
      T = T;
  end
endmodule

SQRT/rcct.v
module rcct(
            input clk,
            input rs,
            input cct,
            input s,
            input [1:0]A,
            input [7:0]S,
            output reg [7:0]R
            );

  always @(negedge clk) begin
    if (rs)
      R = 8'b0;
    if (cct) begin
      R = (R << 2) + {6'b0,A};
    end
    if (s)
      R = S;
    else
      R = R;
  end
endmodule

SQRT/qcct.v
module qcct(
            input clk,
            input rs,
            input sh,
            input S,
            output reg [7:0]Q
            );

  always @(negedge clk) begin
    if (rs)
      Q = 8'b0;
    if (sh) begin
      Q = (Q << 1) + {7'b0,~S};
      //Q = {Q, S};
    end
    else
      Q = Q;
  end
endmodule

SQRT/lsr.v
module lsr(
           input clk,
           input rs,
           input sh,
           input [7:0]i,
           output reg [7:0]o
           );

  always @(negedge clk)
    if (rs)
      o = i;
    else begin
      if (sh)
        o = o << 2;
      else
        o = o;
    end
endmodule

SQRT/SQRT.v
module SQRT(
            input clk,
            input init,
            input rst,
            input [7:0] A,
            output [7:0] Q,
            output [7:0] R,
            output done);

            wire w_rs;
            wire w_cct;
            wire w_dc;
            wire w_s;
            wire w_sh;

            wire [7:0] w_A;
            wire [7:0] T;
            wire [7:0] w_T;
            wire [7:0] w_S;
            wire w_j;

            lsr lsr0 (.clk(clk), .rs(w_rs), .sh(w_sh),
                      .i(A),
                      .o(w_A));

            qcct qcct0 (.clk(clk), .rs(w_rs), .sh(w_sh),
                        .S(w_S[7]),
                        .Q(Q));

            rcct rcct0 (.clk(clk), .rs(w_rs), .cct(w_cct), .s(w_s),
                        .A(w_A[7:6]), .S(w_S),
                        .R(R));

            tcct tcct0 (.clk(clk), .rs(w_rs), .cct(w_cct),
                          .Q(Q),
                          .T(T));

            dec dec0 (.clk(clk), .rs(w_rs), .dc(w_dc),
                      .R(R), .c2(w_T),
                      .S(w_S));

            comp2 comp20 (.clk(clk), .T(T), .cct(w_cct),
                          .c2(w_T));

            cont cont0 (.clk(clk), .rs(w_rs), .sh(w_sh),
                        .j(w_j));

            control_SQRT control_SQRT0 (.clk(clk), .rst(rst), .init(init), .S(w_S[7]), .j(w_j),
                                        .rs(w_rs), .cct(w_cct), .dc(w_dc), .s(w_s), .sh(w_sh), .done(done));
endmodule

SQRT/SQRT_TB.v
`timescale 1ns / 1ps
`define SIMULATION

module SQRT_TB;
  reg clk;
  reg init;
  reg rst;
  reg [7:0] A;

  wire [7:0] Q;
  wire [7:0] R;
  wire done;

  SQRT uut (.clk(clk), .init(init), .rst(rst), .A(A),
            .Q(Q), .R(R), .done(done));
  parameter          PERIOD = 20;
  parameter real DUTY_CYCLE = 0.5;
  parameter          OFFSET = 0;

    event reset_trigger;
    event reset_done_trigger;
    initial begin
      forever begin
        @(reset_trigger);
        @(negedge clk); rst = 1;
        @(negedge clk); rst = 0;
        -> reset_done_trigger;
      end
    end

  initial begin
    clk  = 0;
    init = 0;
    rst  = 0;
    A    = 8'b00010110;
  end

  initial begin
    #OFFSET;
    forever begin
      clk = 1'b0;
      #(PERIOD-(PERIOD*DUTY_CYCLE)) clk = 1'b1;
      #(PERIOD*DUTY_CYCLE);
    end
  end

  reg [20:0] i;
  initial begin
    #10 -> reset_trigger;
    @ (reset_done_trigger);
    @ (posedge clk); init = 0;
    @ (posedge clk); init = 1;
    for (i = 0; i < 2; i = i + 1) begin
      @ (posedge clk);
    end
    init = 0;
    for (i = 0; i < 25; i = i + 1) begin
      @ (posedge clk);
    end
  end


  initial begin: TEST_CASE
    $dumpfile("SQRT_TB.vcd");
    $dumpvars(-1, uut);
    #((PERIOD*DUTY_CYCLE)*200)$finish;
  end
endmodule

SQRT/SQRT_TB.vcd
$date
	Thu Jul 16 08:27:05 2026
$end
$version
	Icarus Verilog
$end
$timescale
	1ps
$end
$scope module SQRT_TB $end
$scope module uut $end
$var wire 8 ! A [7:0] $end
$var wire 1 " clk $end
$var wire 1 # init $end
$var wire 1 $ rst $end
$var wire 1 % w_sh $end
$var wire 1 & w_s $end
$var wire 1 ' w_rs $end
$var wire 1 ( w_j $end
$var wire 1 ) w_dc $end
$var wire 1 * w_cct $end
$var wire 8 + w_T [7:0] $end
$var wire 8 , w_S [7:0] $end
$var wire 8 - w_A [7:0] $end
$var wire 1 . done $end
$var wire 8 / T [7:0] $end
$var wire 8 0 R [7:0] $end
$var wire 8 1 Q [7:0] $end
$scope module comp20 $end
$var wire 1 " clk $end
$var wire 1 * cct $end
$var wire 8 2 T [7:0] $end
$var reg 8 3 c2 [7:0] $end
$upscope $end
$scope module cont0 $end
$var wire 1 " clk $end
$var wire 1 % sh $end
$var wire 1 ' rs $end
$var wire 1 ( j $end
$var reg 3 4 h [2:0] $end
$upscope $end
$scope module control_SQRT0 $end
$var wire 1 5 S $end
$var wire 1 " clk $end
$var wire 1 # init $end
$var wire 1 ( j $end
$var wire 1 $ rst $end
$var parameter 3 6 ASIG $end
$var parameter 3 7 CHECK1 $end
$var parameter 3 8 CHECK2 $end
$var parameter 3 9 CONCAT $end
$var parameter 3 : DEC $end
$var parameter 3 ; DONE $end
$var parameter 3 < SHIFT $end
$var parameter 3 = START $end
$var reg 1 * cct $end
$var reg 4 > count [3:0] $end
$var reg 1 ) dc $end
$var reg 1 . done $end
$var reg 1 ' rs $end
$var reg 1 & s $end
$var reg 1 % sh $end
$var reg 4 ? state [3:0] $end
$upscope $end
$scope module dec0 $end
$var wire 8 @ c2 [7:0] $end
$var wire 1 " clk $end
$var wire 1 ) dc $end
$var wire 1 ' rs $end
$var wire 8 A R [7:0] $end
$var reg 8 B S [7:0] $end
$upscope $end
$scope module lsr0 $end
$var wire 1 " clk $end
$var wire 8 C i [7:0] $end
$var wire 1 ' rs $end
$var wire 1 % sh $end
$var reg 8 D o [7:0] $end
$upscope $end
$scope module qcct0 $end
$var wire 1 E S $end
$var wire 1 " clk $end
$var wire 1 ' rs $end
$var wire 1 % sh $end
$var reg 8 F Q [7:0] $end
$upscope $end
$scope module rcct0 $end
$var wire 2 G A [1:0] $end
$var wire 8 H S [7:0] $end
$var wire 1 * cct $end
$var wire 1 " clk $end
$var wire 1 ' rs $end
$var wire 1 & s $end
$var reg 8 I R [7:0] $end
$upscope $end
$scope module tcct0 $end
$var wire 8 J Q [7:0] $end
$var wire 1 * cct $end
$var wire 1 " clk $end
$var wire 1 ' rs $end
$var reg 8 K T [7:0] $end
$upscope $end
$upscope $end
$upscope $end
$enddefinitions $end
$comment Show the parameter values. $end
$dumpall
b0 =
b101 <
b111 ;
b10 :
b1 9
b110 8
b11 7
b100 6
$end
#0
$dumpvars
bx K
bx J
bx I
b0 H
bx G
bx F
0E
bx D
b10110 C
b0 B
bx A
bx @
bx ?
bx >
05
bx 4
bx 3
bx 2
bx 1
bx 0
bx /
x.
bx -
b0 ,
bx +
x*
0)
x(
0'
x&
x%
0$
0#
0"
b10110 !
$end
#10000
0.
0%
0&
0*
1'
b0 ?
1"
#20000
b0 G
b0 /
b0 2
b0 K
b0 0
b0 A
b0 I
b0 1
b0 F
b0 J
b10110 -
b10110 D
1$
0"
#30000
0(
b100 4
1"
#40000
0$
0"
#50000
b0 >
1"
#60000
0"
#70000
1#
1"
#80000
0"
#90000
1*
0'
b1 ?
1"
#100000
b11111111 +
b11111111 3
b11111111 @
b1 /
b1 2
b1 K
0"
#110000
1)
0*
0#
b10 ?
1"
#120000
15
1E
b11111111 ,
b11111111 B
b11111111 H
0"
#130000
0)
b11 ?
1"
#140000
0"
#150000
1%
b101 ?
1"
#160000
b1 G
b1011000 -
b1011000 D
0"
#170000
0%
b11 4
b110 ?
1"
#180000
0"
#190000
1*
b1 ?
1"
#200000
b1 0
b1 A
b1 I
0"
#210000
1)
0*
b10 ?
1"
#220000
05
0E
b0 ,
b0 B
b0 H
0"
#230000
0)
b11 ?
1"
#240000
0"
#250000
1&
b100 ?
1"
#260000
b0 0
b0 A
b0 I
0"
#270000
1%
0&
b101 ?
1"
#280000
b1100000 -
b1100000 D
b1 1
b1 F
b1 J
0"
#290000
0%
b10 4
b110 ?
1"
#300000
0"
#310000
1*
b1 ?
1"
#320000
b1 0
b1 A
b1 I
b101 /
b101 2
b101 K
0"
#330000
1)
0*
b10 ?
1"
#340000
0"
#350000
0)
b11 ?
1"
#360000
0"
#370000
1&
b100 ?
1"
#380000
b0 0
b0 A
b0 I
0"
#390000
1%
0&
b101 ?
1"
#400000
b10 G
b10000000 -
b10000000 D
b11 1
b11 F
b11 J
0"
#410000
0%
b1 4
b110 ?
1"
#420000
0"
#430000
1*
b1 ?
1"
#440000
b10 0
b10 A
b10 I
b1101 /
b1101 2
b1101 K
b11111011 +
b11111011 3
b11111011 @
0"
#450000
1)
0*
b10 ?
1"
#460000
15
1E
b11111101 ,
b11111101 B
b11111101 H
0"
#470000
0)
b11 ?
1"
#480000
0"
#490000
1%
b101 ?
1"
#500000
b0 G
b110 1
b110 F
b110 J
b0 -
b0 D
0"
#510000
0%
b110 ?
1(
b0 4
1"
#520000
0"
#530000
1.
b111 ?
1"
#540000
0"
#550000
b1 >
1"
#560000
0"
#570000
b10 >
1"
#580000
0"
#590000
b11 >
1"
#600000
0"
#610000
b100 >
1"
#620000
0"
#630000
b101 >
1"
#640000
0"
#650000
b110 >
1"
#660000
0"
#670000
b111 >
1"
#680000
0"
#690000
b1000 >
1"
#700000
0"
#710000
b1001 >
1"
#720000
0"
#730000
0.
1'
b0 ?
b1010 >
1"
#740000
05
0E
b0 ,
b0 B
b0 H
b0 /
b0 2
b0 K
b0 0
b0 A
b0 I
b0 1
b0 F
b0 J
b10110 -
b10110 D
0"
#750000
b0 >
0(
b100 4
1"
