SUMADOR/control_SUM.v
module control_SUM(
            input clk,
            input rst,
            input init,
            input h,

            output reg rs,
            output reg sh,
            output reg done
            );

parameter CHECK = 2'b00;
parameter LOAD  = 2'b01;
parameter CALC  = 2'b10;
parameter DONE  = 2'b11;

reg [1:0]state;

initial begin
  rs   = 0;
  sh   = 0;
  done = 0;

  state = 0;
end

reg [3:0]count;

  always @(posedge clk) begin
    if (rst)
    state = CHECK;
    else begin
    case(state)

    CHECK: begin
      count = 0;
      if (init) begin
        state = LOAD;
      end
      else state = CHECK;
    end

    LOAD:
      state = CALC;

    CALC: begin
      if (h) begin
        state = DONE;
      end
      else
        state = CALC;
    end

    DONE:begin
      count = count + 1;
      if (count>9)
        state = CHECK;
      else
        state = DONE;
      end

    default:
      state = CHECK;

    endcase
  end
end

always @ (state) begin
    case (state)

      CHECK: begin
        rs  = 0;
        sh  = 0;
        done= 0;
      end

      LOAD: begin
        rs  = 1;
        sh  = 0;
        done= 0;
      end

      CALC: begin
        rs  = 0;
        sh  = 1;
        done= 0;
      end

      DONE: begin
        rs  = 0;
        sh  = 0;
        done= 1;
      end
    endcase
  end
endmodule

SUMADOR/cont.v
module cont(
            input clk,
            input rs,
            input sh,
            output reg [3:0] j,
            output wire h
            );

always @(posedge clk) begin
  if (rs)
    j = 4'd0;
  else if (sh)
    if (j<4)
      j = j +4'd1;
  else
  j = j;
end

assign h = (j == 4);
endmodule

SUMADOR/carr.v
module carr(
            input clk,
            input rs,
            input sh,
            input Coutt,
            output reg Cin
            );

always @(negedge clk) begin
  if (rs)
    Cin = 1'b0;
  else if (sh)
    Cin = Coutt;
end
endmodule

SUMADOR/acc.v
module acc(
            input clk,
            input rs,
            input sh,
            input [3:0]j,
            input Sj,
            output reg [3:0]S
            );

always @(negedge clk) begin
  if (rs)
    S = 3'b0;
  else if (sh)
    S[j] = Sj;
end
endmodule

SUMADOR/comp.v
module comp(
            input A,
            input B,
            input Cin,
            output reg S,
            output reg Coutt
            );

always @(*) begin
  if (A == B) begin
    if (A == 1'b1) begin
      S = Cin;
      Coutt = 1'b1;
    end
    else begin
      S = Cin;
      Coutt = 1'b0;
    end
  end

  else begin
    if (Cin == 1'b1) begin
      S = 1'b0;
      Coutt = 1'b1;
    end
    else begin
      S = 1'b1;
      Coutt = 1'b0;
    end
  end
end
endmodule

SUMADOR/SUM.v
 module SUM (
             input clk,
             input init,
             input rst,
             input [3:0] A,
             input [3:0] B,
             output [3:0] S,
             output Cout,
             output done);

             wire w_rs;
             wire w_sh;
             wire w_h;
             wire [3:0] w_j;
             wire w_Sj;
             wire w_Coutt;
             wire w_Cin;

             wire w_A = A[w_j];
             wire w_B = B[w_j];

             comp comp0 (.A(w_A), . B(w_B), .Cin(w_Cin),
                        .S(w_Sj), .Coutt(w_Coutt)
                        );

             acc acc0 (.clk(clk), .rs(w_rs), .sh(w_sh),
                       .j(w_j),
                       .Sj(w_Sj), .S(S));

             carr carr0 (.clk(clk), .rs(w_rs), .sh(w_sh),
                         .Coutt(w_Coutt), .Cin(w_Cin));

             cont cont0 (.clk(clk), .rs(w_rs), .sh(w_sh),
                         .j(w_j),
                         .h(w_h));

             control_SUM control_SUM0 (.clk(clk), .rst(w_rs), .init(init),
                                       .h(w_h), .sh(w_sh), .rs(w_rs), .done(done));
endmodule

SUMADOR/SUM_TB.v
`timescale 1ns / 1ps
`define SIMULATION

module SUM_TB;
  reg clk;
  reg init;
  reg rst;
  reg [3:0] A;
  reg [3:0] B;

  wire [3:0] S;
  wire Cout;
  wire done;

  SUM uut (.clk(clk), .init(init), .rst(rst), .A(A), .B(B),
            .S(S), .Cout(Cout), .done(done));
  parameter          PERIOD = 20;
  parameter real DUTY_CYCLE = 0.5;
  parameter          OFFSET = 0;

    event reset_trigger;
    event reset_done_trigger;
    initial begin
      forever begin
        @(reset_trigger);
        @(negedge clk); rst = 1;
        @(negedge clk); rst = 0;
        -> reset_done_trigger;
      end
    end

  initial begin
    clk = 0;
    init = 0;
    rst = 0;
    A = 4'b0101;
    B = 4'b0011;
  end

  initial begin
    #OFFSET;
    forever begin
      clk = 1'b0;
      #(PERIOD-(PERIOD*DUTY_CYCLE)) clk = 1'b1;
      #(PERIOD*DUTY_CYCLE);
    end
  end

  reg [20:0] i;
  initial begin
    #10 -> reset_trigger;
    @ (reset_done_trigger);
    @ (posedge clk); init = 0;
    @ (posedge clk); init = 1;
    for (i = 0; i < 2; i = i + 1) begin
      @ (posedge clk);
    end
    init = 0;
    for (i = 0; i < 17; i = i + 1) begin
      @ (posedge clk);
    end
  end


  initial begin: TEST_CASE
    $dumpfile("SUM_TB.vcd");
    $dumpvars(-1, uut);
    #((PERIOD*DUTY_CYCLE)*120)$finish;
  end
endmodule

SUMADOR/SUM_TB.vcd
$date
	Thu Jul 16 09:45:00 2026
$end
$version
	Icarus Verilog
$end
$timescale
	1ps
$end
$scope module SUM_TB $end
$scope module uut $end
$var wire 4 ! A [3:0] $end
$var wire 4 " B [3:0] $end
$var wire 1 # Cout $end
$var wire 1 $ clk $end
$var wire 1 % init $end
$var wire 1 & rst $end
$var wire 1 ' w_sh $end
$var wire 1 ( w_rs $end
$var wire 4 ) w_j [3:0] $end
$var wire 1 * w_h $end
$var wire 1 + w_Sj $end
$var wire 1 , w_Coutt $end
$var wire 1 - w_Cin $end
$var wire 1 . w_B $end
$var wire 1 / w_A $end
$var wire 1 0 done $end
$var wire 4 1 S [3:0] $end
$scope module acc0 $end
$var wire 1 $ clk $end
$var wire 1 ' sh $end
$var wire 1 ( rs $end
$var wire 4 2 j [3:0] $end
$var wire 1 + Sj $end
$var reg 4 3 S [3:0] $end
$upscope $end
$scope module carr0 $end
$var wire 1 $ clk $end
$var wire 1 ' sh $end
$var wire 1 ( rs $end
$var wire 1 , Coutt $end
$var reg 1 - Cin $end
$upscope $end
$scope module comp0 $end
$var wire 1 / A $end
$var wire 1 . B $end
$var wire 1 - Cin $end
$var reg 1 , Coutt $end
$var reg 1 + S $end
$upscope $end
$scope module cont0 $end
$var wire 1 $ clk $end
$var wire 1 ' sh $end
$var wire 1 ( rs $end
$var wire 1 * h $end
$var reg 4 4 j [3:0] $end
$upscope $end
$scope module control_SUM0 $end
$var wire 1 $ clk $end
$var wire 1 * h $end
$var wire 1 % init $end
$var wire 1 ( rst $end
$var parameter 2 5 CALC $end
$var parameter 2 6 CHECK $end
$var parameter 2 7 DONE $end
$var parameter 2 8 LOAD $end
$var reg 4 9 count [3:0] $end
$var reg 1 0 done $end
$var reg 1 ( rs $end
$var reg 1 ' sh $end
$var reg 2 : state [1:0] $end
$upscope $end
$upscope $end
$upscope $end
$enddefinitions $end
$comment Show the parameter values. $end
$dumpall
b1 8
b11 7
b0 6
b10 5
$end
#0
$dumpvars
b0 :
bx 9
bx 4
bx 3
bx 2
bx 1
00
x/
x.
x-
x,
x+
x*
bx )
0(
0'
0&
0%
0$
z#
b11 "
b101 !
$end
#10000
b0 9
1$
#20000
1&
0$
#30000
1$
#40000
0&
0$
#50000
1$
#60000
0$
#70000
1%
1$
#80000
0$
#90000
1(
b1 :
1$
#100000
0,
1+
0-
b0 1
b0 3
0$
#110000
0(
1,
0+
0%
b0 :
0*
1.
1/
b0 )
b0 2
b0 4
1$
