DIVISOR/control_DIV.v
module control_DIV(
                   input clk,
                   input rst,
                   input init,
                   input DP,

                   output reg rs,
                   output reg de,
                   output reg ac,
                   output reg done
                   );
  parameter CHECK = 3'b000;
  parameter START = 3'b001;
  parameter DEC   = 3'b010;
  parameter ACC   = 3'b011;
  parameter END   = 3'b100;

  reg [2:0] state;

  initial begin
    rs = 0;
    de = 0;
    ac = 0;
    done = 0;

    state = 0;
  end

  reg [3:0]count;

  always @(posedge clk) begin
    if (rst)
      state = START;
    else begin
      case(state)

      START:begin
        count=0;
        if (init)
          state = DEC;
        else
          state = START;
      end

      DEC:
        state = CHECK;

      CHECK:begin
        if (DP)
          state = END;
        else
          state = ACC;
      end

      END:begin
        count = count + 1;
        if (count>9)
          state = START;
        else
          state = END;
      end

      ACC:
        state = DEC;

      default:
        state = START;

      endcase
    end
  end

  always @ (state) begin
    case (state)

      START:begin
        rs   = 1;
        de   = 0;
        ac   = 0;
        done = 0;
      end

      DEC:begin
        rs   = 0;
        de   = 1;
        ac   = 0;
        done = 0;
      end

      CHECK:begin
        rs   = 0;
        de   = 0;
        ac   = 0;
        done = 0;
      end

      ACC:begin
        rs   = 0;
        de   = 0;
        ac   = 1;
        done = 0;
      end

      END:begin
        rs   = 0;
        de   = 0;
        ac   = 0;
        done = 1;
      end

      default:begin
        rs   = 0;
        de   = 0;
        ac   = 0;
        done = 0;
      end
    endcase
  end
endmodule

DIVISOR/acc.v
module acc(
           input clk,
           input rs,
           input ac,
           output [15:0]R
           );
  initial R = 0;

  always @ (negedge clk)
    if (rs)
      r = 0;
    else
      if (ac)
        R = R + 1;
      else
        R = R;
    end
endmodule

DIVISOR/dec.v
module dec(
           input clk,
           input rs,
           input de,
           input [15:0]c2,
           input [15:0]NUM,
           output reg [15:0]DP
           );
  initial DP = 0;

  always @ (negedge clk)
    if (rs)
      DP = NUM;
    else begin
      if (de)
        DP = DP + c2;
      else
        DP = DP;
    end
endmodule

DIVISOR/comp2.v
module comp2(
             input [14:0]DEN,
             output [15:0]c2 
             );

  always @ (*) begin
    c2 = ~DEN + 1
  end
endmodule

DIVISOR/DIV.v
module DIV(
           input clk,
           input init,
           input rst,
           input [15:0] NUM,
           input [14:0] DEN,
           output [15:0] R,
           output done);

           wire w_rs;
           wire w_de;
           wire w_ac;

           wire [15:0] w_DEN;
           wire [15:0] w_DP;

           comp2 comp20 (.DEN(DEN),
                         .c2(w_DEN));
           dec dec0 (.clk(clk), .rs(w_rs), .de(w_de), .c2(w_DEN), .NUM(NUM),
                     .DP(w_DP));
           acc acc0 (.clk(clk), .rs(w_rs), .ac(w_ac),
                     .R(R));
           control_DIV control_DIV0 (.clk(clk), .rst(rst), .init(init), .DP(w_DP[15]),
                                     .rs(w_rs), .de(w_de), .ac(w_ac), .done(done));
endmodule

DIVISOR/DIV_TB.v
`timescale 1ns / 1ps
`define SIMULATION

module DIV_TB;
  reg clk;
  reg init;
  reg rst;
  reg [15:0] NUM;
  reg [14:0] DEN;

  wire [15:0] R;
  wire done;

  DIV uut (.clk(clk), .init(init), .rst(rst), .NUM(NUM), .DEN(DEN),
           .R(R), .done(done));
  parameter PERIOD          = 20;
  parameter real DUTY_CYCLE = 0.5;
  parameter OFFSET          = 0;

  event reset_trigger;
  event reset_done_trigger;
  initial begin
    forever begin
      @(reset_trigger);
      @(negedge clk);
        rst = 1;
      @(negedge clk);
        rst = 0;
        -> reset_done_trigger;
    end
  end

  initial begin
    clk = 0;
    init = 0;
    rst = 0;
    NUM = 16'b0000000000010111;
    DEN = 16'b0000000000000111;
  end

  initial begin
    #OFFSET;
    forever begin
      clk = 1'b0;
      #(PERIOD-(PERIOD*DUTY_CYCLE)) clk = 1'b1;
      #(PERIOD*DUTY_CYCLE);
    end
  end


  reg [20:0] i;
  initial begin
    #10 -> reset_trigger;
    @ (reset_done_trigger);
    @ (posedge clk); init = 0;
    @ (posedge clk); init = 1;
    for (i = 0; i < 2; i = i + 1) begin
      @ (posedge clk);
    end
    init = 0;
    for (i = 0; i < 17; i = i + 1) begin
      @ (posedge clk);
    end
  end

  initial begin: TEST_CASE
    $dumpfile("DIV_TB.vcd");
    $dumpvars(-1,uut);
    #((PERIOD*DUTY_CYCLE)*120)$finish;
  end
endmodule

DIVISOR/DIV_TB.vcd
$date
	Wed Jul 15 21:13:41 2026
$end
$version
	Icarus Verilog
$end
$timescale
	1ps
$end
$scope module DIV_TB $end
$scope module uut $end
$var wire 15 ! DEN [14:0] $end
$var wire 16 " NUM [15:0] $end
$var wire 1 # clk $end
$var wire 1 $ init $end
$var wire 1 % rst $end
$var wire 1 & w_rs $end
$var wire 1 ' w_de $end
$var wire 1 ( w_ac $end
$var wire 16 ) w_DP [15:0] $end
$var wire 16 * w_DEN [15:0] $end
$var wire 1 + done $end
$var wire 16 , R [15:0] $end
$scope module acc0 $end
$var wire 1 # clk $end
$var wire 1 & rs $end
$var wire 1 ( ac $end
$var reg 16 - R [15:0] $end
$upscope $end
$scope module comp20 $end
$var wire 15 . DEN [14:0] $end
$var reg 16 / c2 [15:0] $end
$upscope $end
$scope module control_DIV0 $end
$var wire 1 0 DP $end
$var wire 1 # clk $end
$var wire 1 $ init $end
$var wire 1 % rst $end
$var parameter 3 1 ACC $end
$var parameter 3 2 CHECK $end
$var parameter 3 3 DEC $end
$var parameter 3 4 END $end
$var parameter 3 5 START $end
$var reg 1 ( ac $end
$var reg 4 6 count [3:0] $end
$var reg 1 ' de $end
$var reg 1 + done $end
$var reg 1 & rs $end
$var reg 3 7 state [2:0] $end
$upscope $end
$scope module dec0 $end
$var wire 16 8 NUM [15:0] $end
$var wire 16 9 c2 [15:0] $end
$var wire 1 # clk $end
$var wire 1 ' de $end
$var wire 1 & rs $end
$var reg 16 : DP [15:0] $end
$upscope $end
$upscope $end
$upscope $end
$enddefinitions $end
$comment Show the parameter values. $end
$dumpall
b1 5
b100 4
b10 3
b0 2
b11 1
$end
#0
$dumpvars
b0 :
b1111111111111001 9
b10111 8
b0 7
bx 6
00
b1111111111111001 /
b111 .
b0 -
b0 ,
0+
b1111111111111001 *
b0 )
0(
0'
0&
0%
0$
0#
b10111 "
b111 !
$end
#10000
1(
b11 7
1#
#20000
b1 ,
b1 -
1%
0#
#30000
0(
1&
b1 7
1#
#40000
0%
b10111 )
b10111 :
b0 ,
b0 -
0#
#50000
b0 6
1#
#60000
0#
#70000
1$
1#
#80000
0#
#90000
1'
0&
b10 7
1#
#100000
b10000 )
b10000 :
0#
#110000
0'
0$
b0 7
1#
#120000
0#
#130000
1(
b11 7
1#
#140000
b1 ,
b1 -
0#
#150000
0(
1'
b10 7
1#
#160000
b1001 )
b1001 :
0#
#170000
0'
b0 7
1#
#180000
0#
#190000
1(
b11 7
1#
#200000
b10 ,
b10 -
0#
#210000
0(
1'
b10 7
1#
#220000
b10 )
b10 :
0#
#230000
0'
b0 7
1#
#240000
0#
#250000
1(
b11 7
1#
#260000
b11 ,
b11 -
0#
#270000
0(
1'
b10 7
1#
#280000
10
b1111111111111011 )
b1111111111111011 :
0#
#290000
0'
b0 7
1#
#300000
0#
#310000
1+
b100 7
1#
#320000
0#
#330000
b1 6
1#
#340000
0#
#350000
b10 6
1#
#360000
0#
#370000
b11 6
1#
#380000
0#
#390000
b100 6
1#
#400000
0#
#410000
b101 6
1#
#420000
0#
#430000
b110 6
1#
#440000
0#
#450000
b111 6
1#
#460000
0#
#470000
b1000 6
1#
#480000
0#
#490000
b1001 6
1#
#500000
0#
#510000
0+
1&
b1 7
b1010 6
1#
#520000
00
b10111 )
b10111 :
b0 ,
b0 -
0#
#530000
b0 6
1#
