MULTIPLICADOR/control_MULT.v
module control_MULT(
                    input clk,
                    input rst,
                    input init,
                    input B,
                    input z,

                    output reg rs,
                    output reg sh,
                    output reg ad,
                    output reg done
                    );

parameter START = 3'b000;
parameter CHECK = 3'b001;
parameter SHIFT = 3'b010;
parameter ADD   = 3'b011;
parameter CHECK2 = 3'b100;
parameter END  = 3'b101;

reg [2:0]state;

initial begin
  rs = 0;
  sh = 0;
  ad = 0;
  done = 0;

  state = 0;
end

reg [3:0]count;

  always @(posedge clk) begin
    if (rst)
      state = START;
    else begin
      case(state)

      START:begin
        count=0;
        if (init)
          state = CHECK;
        else
          state = START;
      end

      CHECK:
        if (B)
          state = ADD;
        else
          state = SHIFT;

      ADD:
        state = SHIFT;

      SHIFT:
        state = CHECK2;

      CHECK2:
        if (z)
          state = END;
        else
          state = CHECK;

      END:begin
        count = count + 1;
        if (count>9)
          state = START;
        else
          state = END;
      end

      default:
        state = START;

      endcase
    end
  end

  always @ (state) begin
    case (state)

      START:begin
        rs   = 1;
        sh   = 0;
        ad   = 0;
        done = 0;
      end

      CHECK:begin
        rs   = 0;
        sh   = 0;
        ad   = 0;
        done = 0;
      end

      ADD:begin
        rs   = 0;
        sh   = 0;
        ad   = 1;
        done = 0;
      end

      SHIFT:begin
        rs   = 0;
        sh   = 1;
        ad   = 0;
        done = 0;
      end

      CHECK2:begin
        rs   = 0;
        sh   = 0;
        ad   = 0;
        done = 0;
      end

      END:begin
        rs   = 0;
        sh   = 0;
        ad   = 0;
        done = 1;
      end

      default:begin
        rs   = 0;
        sh   = 0;
        ad   = 0;
        done = 0;
      end
    endcase
  end
endmodule

MULTIPLICADOR/acc.v
module acc(
           input clk,
           input rs,
           input ad,
           input [31:0]A,
           output [31:0]r
           );
  initial r = 0;

  always @ (negedge clk)
    if (rs)
      r = 0;
    else begin
      if (ad)
        r = r + A;
      else
        r = r;
    end
endmodule

MULTIPLICADOR/comp.v
module comp(
            input [15:0]B,
            output z
            );

  always @ (*) begin
    if (B==0)
      z=1;
    else
      z=0;
  end
endmodule

SQRT/lsr.v
module lsr(
           input clk,
           input rs,
           input sh,
           input [7:0]i_A,
           output reg [7:0]o_A
           );

  always @(negedge clk)
    if (rs)
      o_A = i_A;
    else begin
      if (sh)
        o_A = o_A << 2;
      else
        o_A = o_A;
    end
endmodule

MULTIPLICADOR/rsr.v
module rsr(
           input clk,
           input rs,
           input sh,
           input [15:0]i_B,
           output reg [15:0]o_B
           );

  always @(negedge clk)
    if (rs)
      o_B = i_B;
    else begin
      if (sh)
        o_B = o_B >> 1;
      else
        o_B = o_B;
    end
endmodule

MULTIPLICADOR/MULT.v
module MULT(clk, init, rst, A, B, R, done);
  input clk;
  input init;
  input rst;
  input [15:0] A;
  input [15:0] B;
  output [31:0] R;
  output done;

  wire w_rs;
  wire w_sh;
  wire w_ad;

  wire [31:0] w_A;
  wire [15:0] w_B;
  wire w_z;

  rsr rsr0 (.clk(clk), .rs(w_rs), .sh(w_sh), .i_B(B),
            .o_B(w_B));
  lsr lsr0 (.clk(clk), .rs(w_rs), .sh(w_sh), .i_A(A),
            .o_A(w_A));
  comp comp0 (.B(w_B),
              .z(w_z));
  acc acc0 (.clk(clk), .rs(w_rs), .ad(w_ad), .A(w_A),
            .r(R));
  control_MULT control_MULT0 (.clk(clk), .rst(rst), .init(init), .B(w_B[0]), .z(w_z),
                              .rs(w_rs), .sh(w_sh), .ad(w_ad), .done(done));
endmodule

MULTIPLICADOR/MULT_TB.v
`timescale 1ns / 1ps
`define SIMULATION

module MULT_TB;
  reg clk;
  reg init;
  reg rst;
  reg [15:0] A;
  reg [15:0] B;

  wire [31:0] R;
  wire done;

  MULT uut (.clk(clk), .init(init), .rst(rst), .A(A), .B(B),
            .R(R), .done(done));
  parameter          PERIOD = 20;
  parameter real DUTY_CYCLE = 0.5;
  parameter          OFFSET = 0;

    event reset_trigger;
    event reset_done_trigger;
    initial begin
      forever begin
        @(reset_trigger);
        @(negedge clk); rst = 1;
        @(negedge clk); rst = 0;
        -> reset_done_trigger;
      end
    end

  initial begin
    clk = 0;
    init = 0;
    rst = 0;
    A = 16'b0000000000000101;
    B = 16'b0000000000000011;
  end

  initial begin
    #OFFSET;
    forever begin
      clk = 1'b0;
      #(PERIOD-(PERIOD*DUTY_CYCLE)) clk = 1'b1;
      #(PERIOD*DUTY_CYCLE);
    end
  end

  reg [20:0] i;
  initial begin
    #10 -> reset_trigger;
    @ (reset_done_trigger);
    @ (posedge clk); init = 0;
    @ (posedge clk); init = 1;
    for (i = 0; i < 2; i = i + 1) begin
      @ (posedge clk);
    end
    init = 0;
    for (i = 0; i < 17; i = i + 1) begin
      @ (posedge clk);
    end
  end


  initial begin: TEST_CASE
    $dumpfile("MULT_TB.vcd");
    $dumpvars(-1, uut);
    #((PERIOD*DUTY_CYCLE)*120)$finish;
  end
endmodule

MULTIPLICADOR/MULT_TB.vcd
$date
	Wed Jul 15 20:58:56 2026
$end
$version
	Icarus Verilog
$end
$timescale
	1ps
$end
$scope module MULT_TB $end
$scope module uut $end
$var wire 16 ! A [15:0] $end
$var wire 16 " B [15:0] $end
$var wire 1 # clk $end
$var wire 1 $ init $end
$var wire 1 % rst $end
$var wire 1 & w_z $end
$var wire 1 ' w_sh $end
$var wire 1 ( w_rs $end
$var wire 1 ) w_ad $end
$var wire 16 * w_B [15:0] $end
$var wire 32 + w_A [31:0] $end
$var wire 1 , done $end
$var wire 32 - R [31:0] $end
$scope module acc0 $end
$var wire 1 # clk $end
$var wire 1 ( rs $end
$var wire 1 ) ad $end
$var wire 32 . A [31:0] $end
$var reg 32 / r [31:0] $end
$upscope $end
$scope module comp0 $end
$var wire 16 0 B [15:0] $end
$var reg 1 & z $end
$upscope $end
$scope module control_MULT0 $end
$var wire 1 1 B $end
$var wire 1 # clk $end
$var wire 1 $ init $end
$var wire 1 % rst $end
$var wire 1 & z $end
$var parameter 3 2 ADD $end
$var parameter 3 3 CHECK $end
$var parameter 3 4 CHECK2 $end
$var parameter 3 5 END $end
$var parameter 3 6 SHIFT $end
$var parameter 3 7 START $end
$var reg 1 ) ad $end
$var reg 4 8 count [3:0] $end
$var reg 1 , done $end
$var reg 1 ( rs $end
$var reg 1 ' sh $end
$var reg 3 9 state [2:0] $end
$upscope $end
$scope module rsl0 $end
$var wire 1 # clk $end
$var wire 16 : i_A [15:0] $end
$var wire 1 ( rs $end
$var wire 1 ' sh $end
$var reg 32 ; o_A [31:0] $end
$upscope $end
$scope module rsr0 $end
$var wire 1 # clk $end
$var wire 16 < i_B [15:0] $end
$var wire 1 ( rs $end
$var wire 1 ' sh $end
$var reg 16 = o_B [15:0] $end
$upscope $end
$upscope $end
$upscope $end
$enddefinitions $end
$comment Show the parameter values. $end
$dumpall
b0 7
b10 6
b101 5
b100 4
b1 3
b11 2
$end
#0
$dumpvars
b11 =
b11 <
b101 ;
b101 :
b0 9
bx 8
11
b11 0
b0 /
b101 .
b0 -
0,
b101 +
b11 *
0)
1(
0'
0&
0%
0$
0#
b11 "
b101 !
$end
#10000
b0 8
1#
#20000
1%
0#
#30000
1#
#40000
0%
0#
#50000
1#
#60000
0#
#70000
1$
1#
#80000
0#
#90000
0(
b1 9
1#
#100000
0#
#110000
1)
0$
b11 9
1#
#120000
b101 -
b101 /
0#
#130000
0)
1'
b10 9
1#
#140000
b1010 +
b1010 .
b1010 ;
b1 *
b1 0
b1 =
0#
#150000
0'
b100 9
1#
#160000
0#
#170000
b1 9
1#
#180000
0#
#190000
1)
b11 9
1#
#200000
b1111 -
b1111 /
0#
#210000
0)
1'
b10 9
1#
#220000
01
1&
b10100 +
b10100 .
b10100 ;
b0 *
b0 0
b0 =
0#
#230000
0'
b100 9
1#
#240000
0#
#250000
1,
b101 9
1#
#260000
0#
#270000
b1 8
1#
#280000
0#
#290000
b10 8
1#
#300000
0#
#310000
b11 8
1#
#320000
0#
#330000
b100 8
1#
#340000
0#
#350000
b101 8
1#
#360000
0#
#370000
b110 8
1#
#380000
0#
#390000
b111 8
1#
#400000
0#
#410000
b1000 8
1#
#420000
0#
#430000
b1001 8
1#
#440000
0#
#450000
0,
1(
b0 9
b1010 8
1#
#460000
11
0&
b0 -
b0 /
b101 +
b101 .
b101 ;
b11 *
b11 0
b11 =
0#
#470000
b0 8
1#
