BCD_BIN/control_BCD_BIN.v
module control_BCD_BIN (
                    input clk,
                    input init,
                    input rst,
                    input B,
                    input h,

                    output reg rs,
                    output reg asg,
                    output reg crc,
                    output reg cct,
                    output reg sh,
                    output reg done,
                    output reg ch
                    );

parameter START  = 4'b0000;
parameter CONCAT = 4'b0001;
parameter SHIFT  = 4'b0010;
parameter ASIG   = 4'b0011;
parameter CHECK1 = 4'b0100;
parameter COREG  = 4'b0101;
parameter CHECK2 = 4'b0110;
parameter DONE   = 4'b0111;
parameter CARG   = 4'b1000;

reg [3:0]state;

initial begin
  rs  = 0;
  asg = 0;
  crc = 0;
  cct = 0;
  sh  = 0;
  done= 0;
  ch  = 0;

  state = 0;
end

reg [3:0]count;

  always @(posedge clk) begin
    if (rst)
    state = START;
    else begin
    case(state)

    START:begin
      count = 0;
      if (init)begin
        state = CARG;
      end
      else
        state = START;
    end

    CARG:
      state = CONCAT;

    CONCAT:
      state = SHIFT;

    SHIFT:
      state = ASIG;

    ASIG:
      state = CHECK1;

    CHECK1:
      state = COREG;

    COREG:
      state = CHECK2;

    CHECK2:
      if (h)
        state = DONE;
      else
        state = CONCAT;

      DONE:begin
        count = count + 1;
        if (count>9)
          state = START;
        else
          state = DONE;
        end

        default:
          state = START;

        endcase
      end
    end

  always @ (state) begin
    case (state)

      START: begin
        rs  = 1;
        asg = 0;
        crc = 0;
        cct = 0;
        sh  = 0;
        done= 0;
        ch  = 0;
      end

      CARG: begin
        rs  = 0;
        asg = 0;
        crc = 0;
        cct = 0;
        sh  = 0;
        done= 0;
        ch  = 1;
      end

      CONCAT: begin
        rs  = 0;
        asg = 0;
        crc = 0;
        cct = 1;
        sh  = 0;
        done= 0;
        ch  = 0;
      end

      SHIFT: begin
        rs  = 0;
        asg = 0;
        crc = 0;
        cct = 0;
        sh  = 1;
        done= 0;
        ch  = 0;
      end

      ASIG: begin
        rs  = 0;
        asg = 1;
        crc = 0;
        cct = 0;
        sh  = 0;
        done= 0;
        ch  = 0;
      end

      CHECK1: begin
        rs  = 0;
        asg = 0;
        crc = 0;
        cct = 0;
        sh  = 0;
        done= 0;
        ch  = 0;
      end

      COREG: begin
        rs  = 0;
        asg = 0;
        crc = 1;
        cct = 0;
        sh  = 0;
        done= 0;
        ch  = 0;
      end

      CHECK2: begin
        rs  = 0;
        asg = 0;
        crc = 0;
        cct = 0;
        sh  = 0;
        done= 0;
        ch  = 0;
      end

      DONE: begin
        rs  = 0;
        asg = 0;
        crc = 0;
        cct = 0;
        sh  = 0;
        done= 1;
        ch  = 0;
      end

      default: begin
        rs  = 0;
        asg = 0;
        crc = 0;
        cct = 0;
        sh  = 0;
        done= 0;
        ch  = 0;
      end
    endcase
  end
endmodule

BCD_BIN/cont.v
module cont(
            input clk,
            input rs,
            input asg,
            output reg [3:0]j,
            output wire h
            );

  always @ ( posedge clk) begin
    if (rs)
      j = 4'd8;
    else if (asg) begin
      if (j > 0)
        j = j - 4'd1;
      else
        j = j;
    end
  end
assign h = (j==0);
endmodule

BCD_BIN/compb.v
module compb(
            input clk,
            input rs,
            input asg,
            input crc,
            input [7:0] B,
            input [7:0] R,
            output reg [7:0]o
            );

  always @ (negedge clk)
    if (rs)
      o = B;
    else if (asg)
      o = R;
    else
      o = o;
endmodule

BCD_BIN/comp.v
module comp(
            input clk,
            input rs,
            input ch,
            input asg,
            input crc,
            input [3:0]BCD,
            input [3:0]R,
            output reg [3:0]o
            );

  always @ (negedge clk) begin
    if (rs)
      o = 4'b0;
    else if (ch)
      o = BCD;
    else if (asg)
      o = R;
    else if (crc) begin
      if (R >= 4'b1000)
        o = R - 4'b0011;
      else
        o = R;
    end
  end
endmodule

BCD_BIN/cct.v
module cct(
            input clk,
            input rs,
            input ch,
            input cct,
            input sh,
            input [7:0] B,
            input [11:0]BCD,
            input [3:0] C,
            input [3:0] D,
            input [3:0] U,
            output reg [19:0] R
            );

  always @(negedge clk) begin
    if (rs)
      R = 20'b0;
    if (ch)
      R = {BCD, B};
    if (cct)
      R = {C, D, U, B};
    if (sh)
      R = R >> 1;
    else
      R = R;
  end
endmodule

BCD_BIN/BCD_BIN.v
module BCD_BIN(
           input clk,
           input init,
           input rst,
           input [11:0] BCD,
           output [19:0] R,
           output done);

           wire w_rs;
           wire w_asg;
           wire w_crc;
           wire w_cct;
           wire w_sh;
           wire w_h;
           wire w_ch;

           wire [3:0] w_C;
           wire [3:0] w_D;
           wire [3:0] w_U;
           wire [7:0] w_B;

           cct cct0 (.clk(clk), .rs(w_rs), .cct(w_cct), .sh(w_sh), .ch(w_ch),
                     .B(w_B), .C(w_C), .D(w_D), .U(w_U), .BCD(BCD),
                     .R(R));
           comp comp0 (.clk(clk), .rs(w_rs), .ch(w_ch), .asg(w_asg), .crc(w_crc),
                      .BCD(BCD[11:8]), .R(R[19:16]),
                      .o(w_C));
           comp comp1 (.clk(clk), .rs(w_rs), .ch(w_ch), .asg(w_asg), .crc(w_crc),
                      .BCD(BCD[7:4]), .R(R[15:12]),
                      .o(w_D));
           comp comp2 (.clk(clk), .rs(w_rs), .ch(w_ch), .asg(w_asg), .crc(w_crc),
                      .BCD(BCD[3:0]), .R(R[11:8]),
                      .o(w_U));
           compb compb0 (.clk(clk), .rs(w_rs), .asg(w_asg), .crc(w_crc),
                      .B(8'b00000000), .R(R[7:0]),
                      .o(w_B));
           cont cont0 (.clk(clk), .rs(w_rs), .asg(w_asg),
                       .h(w_h));
           control_BCD_BIN control_BCD_BIN0 (.clk(clk), .rst(rst), .init(init), .h(w_h),
                                            .rs(w_rs), .asg(w_asg), .crc(w_crc), .cct(w_cct), .sh(w_sh), .ch(w_ch),
                                            .done(done));
endmodule

BCD_BIN/BCD_BIN_TB.v
`timescale 1ns / 1ps
`define SIMULATION

module BCD_BIN_TB;
  reg clk;
  reg init;
  reg rst;
  reg [11:0] BCD;

  wire [19:0] R;
  wire done;

  BCD_BIN uut (.clk(clk), .init(init), .rst(rst), .BCD(BCD),
           .R(R), .done(done));
  parameter PERIOD          = 20;
  parameter real DUTY_CYCLE = 0.5;
  parameter OFFSET          = 0;

  event reset_trigger;
  event reset_done_trigger;
  initial begin
    forever begin
      @(reset_trigger);
      @(negedge clk);
        rst = 1;
      @(negedge clk);
        rst = 0;
        -> reset_done_trigger;
    end
  end

  initial begin
    clk = 0;
    init = 0;
    rst = 0;
    BCD = 12'b000101010110;
  end

  initial begin
    #OFFSET;
    forever begin
      clk = 1'b0;
      #(PERIOD-(PERIOD*DUTY_CYCLE)) clk = 1'b1;
      #(PERIOD*DUTY_CYCLE);
    end
  end

  reg [20:0] i;
  initial begin
    #10 -> reset_trigger;
    @ (reset_done_trigger);
    @ (posedge clk); init = 0;
    @ (posedge clk); init = 1;
    for (i = 0; i < 2; i = i + 1) begin
      @ (posedge clk);
    end
    init = 0;
    for (i = 0; i < 17; i = i + 1) begin
      @ (posedge clk);
    end
  end

  initial begin: TEST_CASE
    $dumpfile("BCD_BIN_TB.vcd");
    $dumpvars(-1,uut);
    #((PERIOD*DUTY_CYCLE)*200)$finish;
  end
endmodule

BCD_BIN/BCD_BIN_TB.vcd
$date
	Thu Jul 16 07:25:05 2026
$end
$version
	Icarus Verilog
$end
$timescale
	1ps
$end
$scope module BCD_BIN_TB $end
$scope module uut $end
$var wire 12 ! BCD [11:0] $end
$var wire 1 " clk $end
$var wire 1 # init $end
$var wire 1 $ rst $end
$var wire 1 % w_sh $end
$var wire 1 & w_rs $end
$var wire 1 ' w_h $end
$var wire 1 ( w_crc $end
$var wire 1 ) w_ch $end
$var wire 1 * w_cct $end
$var wire 1 + w_asg $end
$var wire 4 , w_U [3:0] $end
$var wire 4 - w_D [3:0] $end
$var wire 4 . w_C [3:0] $end
$var wire 8 / w_B [7:0] $end
$var wire 1 0 done $end
$var wire 20 1 R [19:0] $end
$scope module cct0 $end
$var wire 12 2 BCD [11:0] $end
$var wire 1 " clk $end
$var wire 1 % sh $end
$var wire 1 & rs $end
$var wire 1 ) ch $end
$var wire 1 * cct $end
$var wire 4 3 U [3:0] $end
$var wire 4 4 D [3:0] $end
$var wire 4 5 C [3:0] $end
$var wire 8 6 B [7:0] $end
$var reg 20 7 R [19:0] $end
$upscope $end
$scope module comp0 $end
$var wire 4 8 BCD [3:0] $end
$var wire 4 9 R [3:0] $end
$var wire 1 " clk $end
$var wire 1 & rs $end
$var wire 1 ( crc $end
$var wire 1 ) ch $end
$var wire 1 + asg $end
$var reg 4 : o [3:0] $end
$upscope $end
$scope module comp1 $end
$var wire 4 ; BCD [3:0] $end
$var wire 4 < R [3:0] $end
$var wire 1 " clk $end
$var wire 1 & rs $end
$var wire 1 ( crc $end
$var wire 1 ) ch $end
$var wire 1 + asg $end
$var reg 4 = o [3:0] $end
$upscope $end
$scope module comp2 $end
$var wire 4 > BCD [3:0] $end
$var wire 4 ? R [3:0] $end
$var wire 1 " clk $end
$var wire 1 & rs $end
$var wire 1 ( crc $end
$var wire 1 ) ch $end
$var wire 1 + asg $end
$var reg 4 @ o [3:0] $end
$upscope $end
$scope module compb0 $end
$var wire 8 A B [7:0] $end
$var wire 8 B R [7:0] $end
$var wire 1 " clk $end
$var wire 1 & rs $end
$var wire 1 ( crc $end
$var wire 1 + asg $end
$var reg 8 C o [7:0] $end
$upscope $end
$scope module cont0 $end
$var wire 1 " clk $end
$var wire 1 & rs $end
$var wire 1 ' h $end
$var wire 1 + asg $end
$var reg 4 D j [3:0] $end
$upscope $end
$scope module control_BCD_BIN0 $end
$var wire 1 E B $end
$var wire 1 " clk $end
$var wire 1 ' h $end
$var wire 1 # init $end
$var wire 1 $ rst $end
$var parameter 4 F ASIG $end
$var parameter 4 G CARG $end
$var parameter 4 H CHECK1 $end
$var parameter 4 I CHECK2 $end
$var parameter 4 J CONCAT $end
$var parameter 4 K COREG $end
$var parameter 4 L DONE $end
$var parameter 4 M SHIFT $end
$var parameter 4 N START $end
$var reg 1 + asg $end
$var reg 1 * cct $end
$var reg 1 ) ch $end
$var reg 4 O count [3:0] $end
$var reg 1 ( crc $end
$var reg 1 0 done $end
$var reg 1 & rs $end
$var reg 1 % sh $end
$var reg 4 P state [3:0] $end
$upscope $end
$upscope $end
$upscope $end
$enddefinitions $end
$comment Show the parameter values. $end
$dumpall
b0 N
b10 M
b111 L
b101 K
b1 J
b110 I
b100 H
b1000 G
b11 F
$end
#0
$dumpvars
b0 P
bx O
zE
bx D
b0 C
b0 B
b0 A
b0 @
b0 ?
b110 >
b0 =
b0 <
b101 ;
b0 :
b0 9
b1 8
b0 7
b0 6
b0 5
b0 4
b0 3
b101010110 2
b0 1
00
b0 /
b0 .
b0 -
b0 ,
0+
0*
0)
0(
x'
1&
0%
0$
0#
0"
b101010110 !
$end
#10000
0'
b1000 D
b0 O
1"
#20000
1$
0"
#30000
1"
#40000
0$
0"
#50000
1"
#60000
0"
#70000
1#
1"
#80000
0"
#90000
1)
0&
b1000 P
1"
#100000
b110 ?
b101 <
b1 9
b110 ,
b110 3
b110 @
b101 -
b101 4
b101 =
b1 .
b1 5
b1 :
b10101011000000000 1
b10101011000000000 7
0"
#110000
0)
1*
0#
b1 P
1"
#120000
0"
#130000
1%
0*
b10 P
1"
#140000
b1011 ?
b1010 <
b0 9
b1010101100000000 1
b1010101100000000 7
0"
#150000
0%
1+
b11 P
1"
#160000
b0 .
b0 5
b0 :
b1010 -
b1010 4
b1010 =
b1011 ,
b1011 3
b1011 @
0"
#170000
0+
b111 D
b100 P
1"
#180000
0"
#190000
1(
b101 P
1"
#200000
b111 -
b111 4
b111 =
b1000 ,
b1000 3
b1000 @
0"
#210000
0(
b110 P
1"
#220000
0"
#230000
1*
b1 P
1"
#240000
b1000 ?
b111 <
b111100000000000 1
b111100000000000 7
0"
#250000
1%
0*
b10 P
1"
#260000
b1100 ?
b11 <
b11110000000000 1
b11110000000000 7
0"
#270000
0%
1+
b11 P
1"
#280000
b11 -
b11 4
b11 =
b1100 ,
b1100 3
b1100 @
0"
#290000
0+
b110 D
b100 P
1"
#300000
0"
#310000
1(
b101 P
1"
#320000
b1001 ,
b1001 3
b1001 @
0"
#330000
0(
b110 P
1"
#340000
0"
#350000
1*
b1 P
1"
#360000
b1001 ?
b11100100000000 1
b11100100000000 7
0"
#370000
1%
0*
b10 P
1"
#380000
b10000000 B
b1100 ?
b1 <
b1110010000000 1
b1110010000000 7
0"
#390000
0%
1+
b11 P
1"
#400000
b1 -
b1 4
b1 =
b1100 ,
b1100 3
b1100 @
b10000000 /
b10000000 6
b10000000 C
0"
#410000
0+
b101 D
b100 P
1"
#420000
0"
#430000
1(
b101 P
1"
#440000
b1001 ,
b1001 3
b1001 @
0"
#450000
0(
b110 P
1"
#460000
0"
#470000
1*
b1 P
1"
#480000
b1001 ?
b1100110000000 1
b1100110000000 7
0"
#490000
1%
0*
b10 P
1"
#500000
b11000000 B
b1100 ?
b0 <
b110011000000 1
b110011000000 7
0"
#510000
0%
1+
b11 P
1"
#520000
b0 -
b0 4
b0 =
b1100 ,
b1100 3
b1100 @
b11000000 /
b11000000 6
b11000000 C
0"
#530000
0+
b100 D
b100 P
1"
#540000
0"
#550000
1(
b101 P
1"
#560000
b1001 ,
b1001 3
b1001 @
0"
#570000
0(
b110 P
1"
#580000
0"
#590000
1*
b1 P
1"
#600000
b1001 ?
b100111000000 1
b100111000000 7
0"
#610000
1%
0*
b10 P
1"
#620000
b11100000 B
b100 ?
b10011100000 1
b10011100000 7
0"
#630000
0%
1+
b11 P
1"
#640000
b100 ,
b100 3
b100 @
b11100000 /
b11100000 6
b11100000 C
0"
#650000
0+
b11 D
b100 P
1"
#660000
0"
#670000
1(
b101 P
1"
#680000
0"
#690000
0(
b110 P
1"
#700000
0"
#710000
1*
b1 P
1"
#720000
0"
#730000
1%
0*
b10 P
1"
#740000
b1110000 B
b10 ?
b1001110000 1
b1001110000 7
0"
#750000
0%
1+
b11 P
1"
#760000
b10 ,
b10 3
b10 @
b1110000 /
b1110000 6
b1110000 C
0"
#770000
0+
b10 D
b100 P
1"
#780000
0"
#790000
1(
b101 P
1"
#800000
0"
#810000
0(
b110 P
1"
#820000
0"
#830000
1*
b1 P
1"
#840000
0"
#850000
1%
0*
b10 P
1"
#860000
b111000 B
b1 ?
b100111000 1
b100111000 7
0"
#870000
0%
1+
b11 P
1"
#880000
b1 ,
b1 3
b1 @
b111000 /
b111000 6
b111000 C
0"
#890000
0+
b1 D
b100 P
1"
#900000
0"
#910000
1(
b101 P
1"
#920000
0"
#930000
0(
b110 P
1"
#940000
0"
#950000
1*
b1 P
1"
#960000
0"
#970000
1%
0*
b10 P
1"
#980000
b10011100 B
b0 ?
b10011100 1
b10011100 7
0"
#990000
0%
1+
b11 P
1"
#1000000
b0 ,
b0 3
b0 @
b10011100 /
b10011100 6
b10011100 C
0"
#1010000
0+
1'
b0 D
b100 P
1"
#1020000
0"
#1030000
1(
b101 P
1"
#1040000
0"
#1050000
0(
b110 P
1"
#1060000
0"
#1070000
10
b111 P
1"
#1080000
0"
#1090000
b1 O
1"
#1100000
0"
#1110000
b10 O
1"
#1120000
0"
#1130000
b11 O
1"
#1140000
0"
#1150000
b100 O
1"
#1160000
0"
#1170000
b101 O
1"
#1180000
0"
#1190000
b110 O
1"
#1200000
0"
#1210000
b111 O
1"
#1220000
0"
#1230000
b1000 O
1"
#1240000
0"
#1250000
b1001 O
1"
#1260000
0"
#1270000
00
1&
b0 P
b1010 O
1"
#1280000
b0 B
b0 1
b0 7
b0 /
b0 6
b0 C
0"
#1290000
0'
b1000 D
b0 O
1"
